setup.py
sneakylang/__init__.py
sneakylang/document.py
sneakylang/err.py
sneakylang/expanders.py
sneakylang/macro.py
sneakylang/macro_caller.py
sneakylang/macro_hook.py
sneakylang/node.py
sneakylang/parser.py
sneakylang/register.py
sneakylang/treebuilder.py
sneakylang.egg-info/PKG-INFO
sneakylang.egg-info/SOURCES.txt
sneakylang.egg-info/dependency_links.txt
sneakylang.egg-info/top_level.txt