Metadata-Version: 1.0
Name: sneakylang
Version: 0.3.0
Summary: Extensible framework for easy creation of extensible WikiLanguages
Home-page: http://projects.almad.net/sneakylang
Author: Lukas Almad Linhart
Author-email: bugs@almad.net
License: BSD
Download-URL: http://www.almad.net/download/sneakylang/sneakylang-0.3.0.tar.gz
Platform: UNKNOWN
Classifier: Development Status :: 4 - Beta
Classifier: Intended Audience :: Developers
Classifier: License :: OSI Approved :: BSD License
Classifier: Operating System :: OS Independent
Classifier: Programming Language :: Python
Classifier: Topic :: Software Development :: Documentation
Classifier: Topic :: Software Development :: Libraries :: Python Modules
Classifier: Topic :: Text Processing
Classifier: Topic :: Text Processing :: Markup :: HTML
Classifier: Topic :: Text Processing :: Markup :: XML
